fast_mime/__init__.py
fast_mime/data/custom.xml
fast_mime/data/patch.json
fast_mime/data/tika.xml
fast_mime-0.1.3.dist-info/LICENSE
fast_mime-0.1.3.dist-info/METADATA
fast_mime-0.1.3.dist-info/WHEEL
fast_mime-0.1.3.dist-info/entry_points.txt
fast_mime-0.1.3.dist-info/RECORD
