Metadata-Version: 2.1
Name: fast-mime
Version: 0.1.3
Summary: 
Author: Chongchen Chen
Author-email: chenkovsky@qq.com
Requires-Python: >=3.11
Classifier: Programming Language :: Python :: 3
Classifier: Programming Language :: Python :: 3.11
Classifier: Programming Language :: Python :: 3.12
